pgUltGUI/Scene.py
pgUltGUI/SceneManager.py
pgUltGUI/__init__.py
pgUltGUI/Widgets/Animation.py
pgUltGUI/Widgets/Button.py
pgUltGUI/Widgets/GridMenu.py
pgUltGUI/Widgets/Image.py
pgUltGUI/Widgets/Item.py
pgUltGUI/Widgets/Label.py
pgUltGUI/Widgets/PopupWindow.py
pgUltGUI/Widgets/ProgressBar.py
pgUltGUI/Widgets/Scroll.py
pgUltGUI/Widgets/Slider.py
pgUltGUI/Widgets/TextInput.py
pgUltGUI/Widgets/Widget.py
pgUltGUI/Widgets/WidgetManager.py
pgUltGUI/Widgets/__init__.py
pgUltGUI-1.4.dist-info/LICENSE
pgUltGUI-1.4.dist-info/METADATA
pgUltGUI-1.4.dist-info/WHEEL
pgUltGUI-1.4.dist-info/top_level.txt
pgUltGUI-1.4.dist-info/RECORD
