Metadata-Version: 2.1
Name: pgUltGUI
Version: 1.4
Summary: Lightweight library for easy creation and use of GUI elements in pygame
Home-page: https://github.com/neuralguy/pgGUI
Author: NeuralGuy
Author-email: neuralguyy@gmail.com
License: UNKNOWN
Platform: UNKNOWN
Classifier: Programming Language :: Python :: 3
Classifier: License :: OSI Approved :: MIT License
Classifier: Operating System :: OS Independent
Requires-Python: >=3.6
License-File: LICENSE
Requires-Dist: numpy
Requires-Dist: pygame-ce
